<?xml version="1.0" encoding="utf-8"?>
<!DOCTYPE hibernate-mapping PUBLIC "-//Hibernate/Hibernate Mapping DTD 3.0//EN"
"http://hibernate.sourceforge.net/hibernate-mapping-3.0.dtd">
<!-- 
    Mapping file autogenerated by MyEclipse Persistence Tools
-->
<hibernate-mapping>
    <class name="com.ymai.hibernate.StoreComnt" table="store_comnt">
        <id name="storeComntId" type="java.lang.Integer">
            <column name="store_comnt_id" />
            <generator class="increment" />
        </id>
        <many-to-one name="user" class="com.ymai.hibernate.User" fetch="select">
            <column name="user_id" />
        </many-to-one>
        <many-to-one name="store" class="com.ymai.hibernate.Store" fetch="select">
            <column name="store_id" not-null="true" />
        </many-to-one>
        <property name="storeComntDetail" type="java.lang.String">
            <column name="store_comnt_detail" length="65535" />
        </property>
        <property name="storeComntTime" type="java.util.Date">
            <column name="store_comnt_time" length="19" not-null="true" />
        </property>
        <property name="storeComntFlag" type="java.lang.Integer">
            <column name="store_comnt_flag" />
        </property>
        <property name="userName" type="java.lang.String">
            <column name="user_name" length="10" />
        </property>
    </class>
</hibernate-mapping>
