<?xml version="1.0" encoding="utf-8"?>
<!DOCTYPE hibernate-mapping PUBLIC "-//Hibernate/Hibernate Mapping DTD 3.0//EN"
"http://hibernate.sourceforge.net/hibernate-mapping-3.0.dtd">
<!-- 
    Mapping file autogenerated by MyEclipse Persistence Tools
-->
<hibernate-mapping>
    <class name="com.ymai.hibernate.Item" table="item">
        <id name="itemId" type="java.lang.Integer">
            <column name="item_id" />
            <generator class="increment" />
        </id>
        <many-to-one name="store" class="com.ymai.hibernate.Store" fetch="select">
            <column name="store_id" not-null="true" />
        </many-to-one>
        <property name="itemName" type="java.lang.String">
            <column name="item_name" length="50" not-null="true" />
        </property>
        <property name="itemImgSrc" type="java.lang.String">
            <column name="item_img_src" length="200" />
        </property>
        <property name="itemDetail" type="java.lang.String">
            <column name="item_detail" length="300" />
        </property>
        <property name="itemPrice" type="java.lang.Double">
            <column name="item_price" precision="12" scale="0" not-null="true" />
        </property>
        <property name="itemDsct" type="java.lang.Double">
            <column name="item_dsct" precision="3" not-null="true" />
        </property>
        <property name="itemWeeklyOrder" type="java.lang.Integer">
            <column name="item_weekly_order" />
        </property>
        <property name="itemTotalOrder" type="java.lang.Integer">
            <column name="item_total_order" />
        </property>
        <property name="itemType" type="java.lang.String">
            <column name="item_type" length="30" />
        </property>
        <property name="itemRecommend" type="java.lang.Integer">
            <column name="item_recommend" />
        </property>
        <property name="itemState" type="java.lang.String">
            <column name="item_state" length="3" />
        </property>
        <set name="orderItemses" inverse="true">
            <key>
                <column name="item_id" />
            </key>
            <one-to-many class="com.ymai.hibernate.OrderItems" />
        </set>
    </class>
</hibernate-mapping>
